{
  "assets": {
    "logos": {
      "club-employes": {
        "default": {
          "value": "/assets/logos/club-employes/logo.svg",
          "type": "asset",
          "description": "Logo principal Club Employés"
        },
        "small": {
          "value": "/assets/logos/club-employes/logo-small.svg",
          "type": "asset",
          "description": "Logo Club Employés version compacte"
        },
        "white": {
          "value": "/assets/logos/club-employes/logo-white.svg",
          "type": "asset",
          "description": "Logo Club Employés version blanche (sur fond sombre)"
        },
        "small-white": {
          "value": "/assets/logos/club-employes/logo-small-white.svg",
          "type": "asset",
          "description": "Logo Club Employés version compacte et blanche"
        }
      },
      "gifteo": {
        "default": {
          "value": "/assets/logos/gifteo/logo.svg",
          "type": "asset",
          "description": "Logo principal Gifteo"
        },
        "small": {
          "value": "/assets/logos/gifteo/logo-small.svg",
          "type": "asset",
          "description": "Logo Gifteo version compacte"
        },
        "white": {
          "value": "/assets/logos/gifteo/logo-white.svg",
          "type": "asset",
          "description": "Logo Gifteo version blanche (sur fond sombre)"
        },
        "small-white": {
          "value": "/assets/logos/gifteo/logo-small-white.svg",
          "type": "asset",
          "description": "Logo Gifteo version compacte et blanche"
        }
      }
    }
  }
}